{
  "qe": {
    "username": "qe",
    "password": "few",
    "created": "2020-06-02 02-16-11"
  },
  "Swarna": {
    "username": "Swarna",
    "password": "Deep",
    "created": "2020-06-02 03-45-16"
  },
  "ewd": {
    "username": "ewd",
    "password": "fggg",
    "created": "2020-06-02 02-17-30"
  },
  "Mukul": {
    "username": "Mukul",
    "password": "Kumar",
    "created": "2020-06-02 02-41-40"
  },
  "dwad": {
    "username": "dwad",
    "password": "awd",
    "created": "2020-06-02 02-43-32"
  },
  "Swapnil": {
    "username": "Swapnil",
    "password": "Sarkar",
    "created": "2020-06-02 02-48-27"
  },
  "dv": {
    "username": "dv",
    "password": "aefc",
    "created": "2020-06-02 02-49-53"
  },
  "": {
    "username": "",
    "password": "",
    "created": "2020-06-02 06-21-21"
  },
  "swapnil sarkar": {
    "username": "swapnil sarkar",
    "password": "banturdol",
    "created": "2020-06-26 22-11-34"
  }
}